CHANGELOG.md
LICENSE
README.md
django_celery_token_bucket/__init__.py
django_celery_token_bucket/apps.py
django_celery_token_bucket/bucket.py
django_celery_token_bucket/decorators.py
django_celery_token_bucket/tasks.py
django_celery_token_bucket/management/__init__.py
django_celery_token_bucket/management/commands/__init__.py
django_celery_token_bucket/management/commands/token_bucket_register_periodic_tasks.py
django_celery_token_bucket/tests/__init__.py
django_celery_token_bucket/tests/test_bucket.py
django_celery_token_bucket/tests/test_tasks.py
django_celery_token_bucket-5.0.0.dist-info/METADATA
django_celery_token_bucket-5.0.0.dist-info/WHEEL
django_celery_token_bucket-5.0.0.dist-info/licenses/LICENSE
django_celery_token_bucket-5.0.0.dist-info/RECORD
