Metadata-Version: 2.4
Name: django-celery-token-bucket
Version: 5.0.0
Summary: A token bucket implementation for celery rate limiting in Django
Project-URL: Homepage, https://github.com/RegioHelden/django-celery-token-bucket
Project-URL: Documentation, https://github.com/RegioHelden/django-celery-token-bucket/blob/main/README.md
Project-URL: Repository, https://github.com/RegioHelden/django-celery-token-bucket.git
Project-URL: Issues, https://github.com/RegioHelden/django-celery-token-bucket/issues
Project-URL: Changelog, https://github.com/RegioHelden/django-celery-token-bucket/blob/main/CHANGELOG.md
Author-email: RegioHelden GmbH <opensource@regiohelden.de>
Maintainer-email: RegioHelden GmbH <opensource@regiohelden.de>
License-Expression: MIT
License-File: LICENSE
Keywords: bucket,celery,django,rate limiting,token
Classifier: Development Status :: 5 - Production/Stable
Classifier: Environment :: Web Environment
Classifier: Framework :: Django
Classifier: Intended Audience :: Developers
Classifier: License :: OSI Approved :: MIT License
Classifier: Operating System :: OS Independent
Classifier: Programming Language :: Python
Classifier: Programming Language :: Python :: 3
Classifier: Programming Language :: Python :: 3.11
Classifier: Programming Language :: Python :: 3.12
Classifier: Programming Language :: Python :: 3.13
Classifier: Topic :: Software Development
Classifier: Topic :: Software Development :: Libraries :: Python Modules
Requires-Python: >=3.11
Requires-Dist: celery<6.0.0,>=5.5.0
Requires-Dist: django-celery-beat<3.0.0,>=2.5.0
Requires-Dist: django<6.1,>=4.2
Requires-Dist: kombu<6.0.0,>=5.5.0
